ragged_buffer-0.4.8.dist-info/METADATA
ragged_buffer-0.4.8.dist-info/WHEEL
ragged_buffer-0.4.8.dist-info/license_files/LICENSE-APACHE
ragged_buffer-0.4.8.dist-info/license_files/LICENSE-MIT
ragged_buffer/__init__.pyi
ragged_buffer/py.typed
ragged_buffer/__init__.py
ragged_buffer/ragged_buffer.cpython-38-x86_64-linux-gnu.so
ragged_buffer-0.4.8.dist-info/RECORD
