Metadata-Version: 2.1
Name: ragged-buffer
Version: 0.4.8
Classifier: Topic :: Scientific/Engineering :: Artificial Intelligence
Classifier: Programming Language :: Rust
Classifier: Programming Language :: Python :: Implementation :: CPython
Requires-Dist: numpy~=1.21
License-File: LICENSE-APACHE
License-File: LICENSE-MIT
Summary: Efficient RaggedBuffer datatype that implements 3D arrays with variable-length 2nd dimension.
Author: Clemens Winter <clemenswinter1@gmail.com>
Author-email: Clemens Winter <clemenswinter1@gmail.com>
License: MIT OR Apache-2.0
Requires-Python: >=3.7
Project-URL: Source Code, https://github.com/entity-neural-network/ragged-buffer
